tesla_coil_simulator/DRSSTC.py
tesla_coil_simulator/__init__.py
tesla_coil_simulator/utils.py
tesla_coil_simulator-0.1.0.dist-info/METADATA
tesla_coil_simulator-0.1.0.dist-info/WHEEL
tesla_coil_simulator-0.1.0.dist-info/top_level.txt
tesla_coil_simulator-0.1.0.dist-info/RECORD
