Metadata-Version: 2.4
Name: tesla-coil-simulator
Version: 0.1.0
Summary: Physics simulator for DRSSTC (Dual Resonant Solid State Tesla Coils) with coupled RLC circuit analysis
Home-page: https://github.com/TeslaCoilResearch/tesla-coil-simulator
Author: Ricky Ding
Author-email: e0134117@u.nus.edu
License: MIT
Keywords: tesla coil,DRSSTC,resonant circuit,RLC simulator,high voltage physics,electrical engineering,physics simulation,coupled resonators
Classifier: Programming Language :: Python :: 3
Classifier: License :: OSI Approved :: MIT License
Classifier: Operating System :: OS Independent
Classifier: Intended Audience :: Science/Research
Classifier: Intended Audience :: Education
Classifier: Topic :: Scientific/Engineering :: Physics
Classifier: Topic :: Scientific/Engineering :: Electronic Design Automation (EDA)
Requires-Python: >=3.8
Requires-Dist: matplotlib
Requires-Dist: numpy
Requires-Dist: scipy
Dynamic: author
Dynamic: author-email
Dynamic: classifier
Dynamic: description
Dynamic: description-content-type
Dynamic: home-page
Dynamic: keywords
Dynamic: license
Dynamic: requires-dist
Dynamic: requires-python
Dynamic: summary
